pyhud-0.1.3.dist-info/LICENSE
pyhud-0.1.3.dist-info/METADATA
pyhud-0.1.3.dist-info/top_level.txt
pyhud-0.1.3.dist-info/RECORD
pyhud-0.1.3.dist-info/WHEEL
pyhud/client.py
pyhud/_internal.py
pyhud/logging.py
pyhud/auto_hook.py
pyhud/run_mode.py
pyhud/exception_handler.py
pyhud/hook.py
pyhud/native.pyi
pyhud/__version__.py
pyhud/__init__.py
pyhud/declarations.py
pyhud/utils.py
pyhud/invocations_handler.py
pyhud/native.cpython-39-aarch64-linux-gnu.so
pyhud/config.py
pyhud/worker/task_manager.py
pyhud/worker/worker.py
pyhud/worker/__init__.py
pyhud/workload_metadata/kubernetes_workload_metadata.py
pyhud/workload_metadata/workload_data.py
pyhud/workload_metadata/__init__.py
pyhud/workload_metadata/aws_workload_matadata.py
pyhud/schemas/requests.py
pyhud/schemas/__init__.py
pyhud/schemas/schema.py
pyhud/schemas/events.py
pyhud/collectors/runtime.py
pyhud/collectors/performance.py
pyhud/collectors/__init__.py
pyhud/collectors/modules.py
