Metadata-Version: 2.1
Name: pyhud
Version: 0.1.3
Requires-Python: >=3.5
License-File: LICENSE
Requires-Dist: aiohttp >=1.0.0
Requires-Dist: requests
